[
 {
  "text": "Una tarde",
  "newLine": true,
  "translation": {
   "text": "Uma tarde",
   "tips": [
    {
     "text": "tarde",
     "translatedText": "tarde (período do dia)",
     "explanation": null
    }
   ]
  }
 },
 {
  "text": ", ",
  "newLine": false,
  "translation": null
 },
 {
  "text": "Ana",
  "newLine": false,
  "translation": {
   "text": "Ana",
   "tips": [
    {
     "text": "Ana",
     "translatedText": "Ana (nome da menina)",
     "explanation": null
    }
   ]
  }
 },
 {
  "text": ", ",
  "newLine": false,
  "translation": null
 },
 {
  "text": "una niña lista",
  "newLine": false,
  "translation": {
   "text": "uma menina esperta",
   "tips": [
    {
     "text": "niña",
     "translatedText": "menina / garota",
     "explanation": null
    },
    {
     "text": "lista",
     "translatedText": "esperta / inteligente",
     "explanation": null
    }
   ]
  }
 },
 {
  "text": " ",
  "newLine": false,
  "translation": null
 },
 {
  "text": "de cinco años",
  "newLine": false,
  "translation": {
   "text": "de cinco anos",
   "tips": [
    {
     "text": "años",
     "translatedText": "anos",
     "explanation": null
    }
   ]
  }
 },
 {
  "text": ", ",
  "newLine": false,
  "translation": null
 },
 {
  "text": "no llegó a casa",
  "newLine": false,
  "translation": {
   "text": "não chegou em casa",
   "tips": [
    {
     "text": "llegó",
     "translatedText": "chegou",
     "explanation": null
    },
    {
     "text": "a casa",
     "translatedText": "em casa / para casa",
     "explanation": null
    }
   ]
  }
 },
 {
  "text": " ",
  "newLine": false,
  "translation": null
 },
 {
  "text": "con su sonrisa de siempre",
  "newLine": false,
  "translation": {
   "text": "com seu sorriso de sempre",
   "tips": [
    {
     "text": "sonrisa",
     "translatedText": "sorriso",
     "explanation": null
    },
    {
     "text": "de siempre",
     "translatedText": "de sempre / habitual",
     "explanation": null
    }
   ]
  }
 },
 {
  "text": ". ",
  "newLine": false,
  "translation": null
 },
 {
  "text": "En vez de eso",
  "newLine": false,
  "translation": {
   "text": "Em vez disso",
   "tips": [
    {
     "text": "En vez de",
     "translatedText": "em vez de",
     "explanation": null
    },
    {
     "text": "eso",
     "translatedText": "isso",
     "explanation": null
    }
   ]
  }
 },
 {
  "text": ", ",
  "newLine": false,
  "translation": null
 },
 {
  "text": "había algo",
  "newLine": false,
  "translation": {
   "text": "havia algo",
   "tips": [
    {
     "text": "había",
     "translatedText": "havia / existia",
     "explanation": null
    },
    {
     "text": "algo",
     "translatedText": "algo / alguma coisa",
     "explanation": null
    }
   ]
  }
 },
 {
  "text": " ",
  "newLine": false,
  "translation": null
 },
 {
  "text": "en su cabeza",
  "newLine": false,
  "translation": {
   "text": "na cabeça dela",
   "tips": [
    {
     "text": "su cabeza",
     "translatedText": "sua cabeça / a cabeça dela",
     "explanation": null
    }
   ]
  }
 },
 {
  "text": ". ",
  "newLine": false,
  "translation": null
 },
 {
  "text": "Así que",
  "newLine": false,
  "translation": {
   "text": "Então / Por isso",
   "tips": [
    {
     "text": "Así que",
     "translatedText": "então / por isso / de modo que",
     "explanation": null
    }
   ]
  }
 },
 {
  "text": " ",
  "newLine": false,
  "translation": null
 },
 {
  "text": "su madre",
  "newLine": false,
  "translation": {
   "text": "sua mãe",
   "tips": [
    {
     "text": "madre",
     "translatedText": "mãe",
     "explanation": null
    }
   ]
  }
 },
 {
  "text": " ",
  "newLine": false,
  "translation": null
 },
 {
  "text": "le preguntó",
  "newLine": false,
  "translation": {
   "text": "perguntou a ela",
   "tips": [
    {
     "text": "le",
     "translatedText": "a ela / para ela",
     "explanation": null
    },
    {
     "text": "preguntó",
     "translatedText": "perguntou",
     "explanation": null
    }
   ]
  }
 },
 {
  "text": ": ",
  "newLine": false,
  "translation": null
 },
 {
  "text": "«",
  "newLine": false,
  "translation": null
 },
 {
  "text": "Hija mía",
  "newLine": false,
  "translation": {
   "text": "Filha minha",
   "tips": [
    {
     "text": "Hija",
     "translatedText": "filha",
     "explanation": null
    },
    {
     "text": "mía",
     "translatedText": "minha",
     "explanation": null
    }
   ]
  }
 },
 {
  "text": ", ",
  "newLine": false,
  "translation": null
 },
 {
  "text": "¿",
  "newLine": false,
  "translation": null
 },
 {
  "text": "estás bien",
  "newLine": false,
  "translation": {
   "text": "você está bem",
   "tips": [
    {
     "text": "estás",
     "translatedText": "você está",
     "explanation": null
    },
    {
     "text": "bien",
     "translatedText": "bem",
     "explanation": null
    }
   ]
  }
 },
 {
  "text": "?",
  "newLine": false,
  "translation": null
 },
 {
  "text": "»",
  "newLine": false,
  "translation": null
 },
 {
  "text": ".",
  "newLine": false,
  "translation": null
 },
 {
  "text": "«",
  "newLine": true,
  "translation": null
 },
 {
  "text": "Sí",
  "newLine": false,
  "translation": {
   "text": "Sim",
   "tips": [
    {
     "text": "Sí",
     "translatedText": "sim",
     "explanation": null
    }
   ]
  }
 },
 {
  "text": ", ",
  "newLine": false,
  "translation": null
 },
 {
  "text": "lo estoy",
  "newLine": false,
  "translation": {
   "text": "estou (sim)",
   "tips": [
    {
     "text": "lo estoy",
     "translatedText": "estou (sim) / estou bem",
     "explanation": null
    }
   ]
  }
 },
 {
  "text": ", ",
  "newLine": false,
  "translation": null
 },
 {
  "text": "mamá",
  "newLine": false,
  "translation": {
   "text": "mamãe",
   "tips": [
    {
     "text": "mamá",
     "translatedText": "mamãe / mãe",
     "explanation": null
    }
   ]
  }
 },
 {
  "text": ". ",
  "newLine": false,
  "translation": null
 },
 {
  "text": "Pero hoy",
  "newLine": false,
  "translation": {
   "text": "Mas hoje",
   "tips": [
    {
     "text": "Pero",
     "translatedText": "mas / porém",
     "explanation": null
    },
    {
     "text": "hoy",
     "translatedText": "hoje",
     "explanation": null
    }
   ]
  }
 },
 {
  "text": " ",
  "newLine": false,
  "translation": null
 },
 {
  "text": "en la escuela",
  "newLine": false,
  "translation": {
   "text": "na escola",
   "tips": [
    {
     "text": "escuela",
     "translatedText": "escola",
     "explanation": null
    }
   ]
  }
 },
 {
  "text": " ",
  "newLine": false,
  "translation": null
 },
 {
  "text": "me di cuenta de que",
  "newLine": false,
  "translation": {
   "text": "percebi que",
   "tips": [
    {
     "text": "me di cuenta de",
     "translatedText": "me dei conta de / percebi",
     "explanation": "Expressão-campeã: \"darse cuenta de\" = \"perceber / dar-se conta de\". NÃO confunda com \"realizar\" (em espanhol \"realizar\" é \"executar/fazer\", não \"perceber\"). Sempre vem com a preposição \"de que\"."
    }
   ]
  }
 },
 {
  "text": " ",
  "newLine": false,
  "translation": null
 },
 {
  "text": "todavía hay",
  "newLine": false,
  "translation": {
   "text": "ainda há",
   "tips": [
    {
     "text": "todavía",
     "translatedText": "ainda",
     "explanation": "Falso amigo perigosíssimo: \"todavía\" = \"AINDA\" (tempo), e NÃO \"todavia\" (= no entanto). Para dizer o nosso \"todavia\", o espanhol usa \"sin embargo\"."
    },
    {
     "text": "hay",
     "translatedText": "há / existe(m)",
     "explanation": null
    }
   ]
  }
 },
 {
  "text": " ",
  "newLine": false,
  "translation": null
 },
 {
  "text": "muchas cosas",
  "newLine": false,
  "translation": {
   "text": "muitas coisas",
   "tips": [
    {
     "text": "muchas",
     "translatedText": "muitas",
     "explanation": null
    },
    {
     "text": "cosas",
     "translatedText": "coisas",
     "explanation": null
    }
   ]
  }
 },
 {
  "text": " ",
  "newLine": false,
  "translation": null
 },
 {
  "text": "que no entiendo",
  "newLine": false,
  "translation": {
   "text": "que não entendo",
   "tips": [
    {
     "text": "entiendo",
     "translatedText": "entendo / compreendo",
     "explanation": null
    }
   ]
  }
 },
 {
  "text": " ",
  "newLine": false,
  "translation": null
 },
 {
  "text": "muy bien",
  "newLine": false,
  "translation": {
   "text": "muito bem",
   "tips": [
    {
     "text": "muy",
     "translatedText": "muito (antes de adjetivo/advérbio)",
     "explanation": null
    },
    {
     "text": "bien",
     "translatedText": "bem",
     "explanation": null
    }
   ]
  }
 },
 {
  "text": "»",
  "newLine": false,
  "translation": null
 },
 {
  "text": ", ",
  "newLine": false,
  "translation": null
 },
 {
  "text": "dijo la niña",
  "newLine": false,
  "translation": {
   "text": "disse a menina",
   "tips": [
    {
     "text": "dijo",
     "translatedText": "disse",
     "explanation": null
    }
   ]
  }
 },
 {
  "text": ".",
  "newLine": false,
  "translation": null
 },
 {
  "text": "«",
  "newLine": true,
  "translation": null
 },
 {
  "text": "¿",
  "newLine": false,
  "translation": null
 },
 {
  "text": "Quieres hablar",
  "newLine": false,
  "translation": {
   "text": "Você quer falar",
   "tips": [
    {
     "text": "Quieres",
     "translatedText": "você quer",
     "explanation": null
    },
    {
     "text": "hablar",
     "translatedText": "falar / conversar",
     "explanation": null
    }
   ]
  }
 },
 {
  "text": " ",
  "newLine": false,
  "translation": null
 },
 {
  "text": "de eso",
  "newLine": false,
  "translation": {
   "text": "sobre isso",
   "tips": [
    {
     "text": "de eso",
     "translatedText": "sobre isso / disso",
     "explanation": null
    }
   ]
  }
 },
 {
  "text": "?",
  "newLine": false,
  "translation": null
 },
 {
  "text": "»",
  "newLine": false,
  "translation": null
 },
 {
  "text": ", ",
  "newLine": false,
  "translation": null
 },
 {
  "text": "preguntó su madre",
  "newLine": false,
  "translation": {
   "text": "perguntou sua mãe",
   "tips": [
    {
     "text": "preguntó",
     "translatedText": "perguntou",
     "explanation": null
    }
   ]
  }
 },
 {
  "text": ".",
  "newLine": false,
  "translation": null
 },
 {
  "text": "«",
  "newLine": true,
  "translation": null
 },
 {
  "text": "Sí",
  "newLine": false,
  "translation": {
   "text": "Sim",
   "tips": [
    {
     "text": "Sí",
     "translatedText": "sim",
     "explanation": null
    }
   ]
  }
 },
 {
  "text": "»",
  "newLine": false,
  "translation": null
 },
 {
  "text": ", ",
  "newLine": false,
  "translation": null
 },
 {
  "text": "respondió la niña",
  "newLine": false,
  "translation": {
   "text": "respondeu a menina",
   "tips": [
    {
     "text": "respondió",
     "translatedText": "respondeu",
     "explanation": null
    }
   ]
  }
 },
 {
  "text": ". ",
  "newLine": false,
  "translation": null
 },
 {
  "text": "«",
  "newLine": false,
  "translation": null
 },
 {
  "text": "Hoy",
  "newLine": false,
  "translation": {
   "text": "Hoje",
   "tips": [
    {
     "text": "Hoy",
     "translatedText": "hoje",
     "explanation": null
    }
   ]
  }
 },
 {
  "text": " ",
  "newLine": false,
  "translation": null
 },
 {
  "text": "la maestra",
  "newLine": false,
  "translation": {
   "text": "a professora",
   "tips": [
    {
     "text": "maestra",
     "translatedText": "professora (do primário)",
     "explanation": null
    }
   ]
  }
 },
 {
  "text": " ",
  "newLine": false,
  "translation": null
 },
 {
  "text": "estaba hablando",
  "newLine": false,
  "translation": {
   "text": "estava falando",
   "tips": [
    {
     "text": "estaba hablando",
     "translatedText": "estava falando",
     "explanation": null
    }
   ]
  }
 },
 {
  "text": " ",
  "newLine": false,
  "translation": null
 },
 {
  "text": "del trabajo",
  "newLine": false,
  "translation": {
   "text": "sobre o trabalho",
   "tips": [
    {
     "text": "del",
     "translatedText": "do (de + el)",
     "explanation": null
    },
    {
     "text": "trabajo",
     "translatedText": "trabalho",
     "explanation": null
    }
   ]
  }
 },
 {
  "text": " ",
  "newLine": false,
  "translation": null
 },
 {
  "text": "y de los empleos",
  "newLine": false,
  "translation": {
   "text": "e sobre os empregos",
   "tips": [
    {
     "text": "empleos",
     "translatedText": "empregos / profissões",
     "explanation": null
    }
   ]
  }
 },
 {
  "text": ", ",
  "newLine": false,
  "translation": null
 },
 {
  "text": "y mis amigos",
  "newLine": false,
  "translation": {
   "text": "e meus amigos",
   "tips": [
    {
     "text": "mis amigos",
     "translatedText": "meus amigos",
     "explanation": null
    }
   ]
  }
 },
 {
  "text": " ",
  "newLine": false,
  "translation": null
 },
 {
  "text": "hablaban todos",
  "newLine": false,
  "translation": {
   "text": "falavam todos",
   "tips": [
    {
     "text": "hablaban",
     "translatedText": "falavam",
     "explanation": null
    },
    {
     "text": "todos",
     "translatedText": "todos",
     "explanation": null
    }
   ]
  }
 },
 {
  "text": " ",
  "newLine": false,
  "translation": null
 },
 {
  "text": "del trabajo de sus padres",
  "newLine": false,
  "translation": {
   "text": "sobre o trabalho dos pais deles",
   "tips": [
    {
     "text": "sus padres",
     "translatedText": "seus pais / os pais deles",
     "explanation": null
    }
   ]
  }
 },
 {
  "text": ", ",
  "newLine": false,
  "translation": null
 },
 {
  "text": "pero entonces",
  "newLine": false,
  "translation": {
   "text": "mas então",
   "tips": [
    {
     "text": "entonces",
     "translatedText": "então / naquele momento",
     "explanation": null
    }
   ]
  }
 },
 {
  "text": " ",
  "newLine": false,
  "translation": null
 },
 {
  "text": "me di cuenta de que",
  "newLine": false,
  "translation": {
   "text": "percebi que",
   "tips": [
    {
     "text": "me di cuenta de",
     "translatedText": "me dei conta de / percebi",
     "explanation": null
    }
   ]
  }
 },
 {
  "text": " ",
  "newLine": false,
  "translation": null
 },
 {
  "text": "¡",
  "newLine": false,
  "translation": null
 },
 {
  "text": "yo no sé",
  "newLine": false,
  "translation": {
   "text": "eu não sei",
   "tips": [
    {
     "text": "yo",
     "translatedText": "eu",
     "explanation": null
    },
    {
     "text": "no sé",
     "translatedText": "não sei",
     "explanation": null
    }
   ]
  }
 },
 {
  "text": " ",
  "newLine": false,
  "translation": null
 },
 {
  "text": "qué haces tú",
  "newLine": false,
  "translation": {
   "text": "o que você faz",
   "tips": [
    {
     "text": "qué",
     "translatedText": "o que / que",
     "explanation": null
    },
    {
     "text": "haces tú",
     "translatedText": "você faz",
     "explanation": null
    }
   ]
  }
 },
 {
  "text": "!",
  "newLine": false,
  "translation": null
 },
 {
  "text": "»",
  "newLine": false,
  "translation": null
 },
 {
  "text": ".",
  "newLine": false,
  "translation": null
 },
 {
  "text": "«",
  "newLine": true,
  "translation": null
 },
 {
  "text": "¡",
  "newLine": false,
  "translation": null
 },
 {
  "text": "Pero claro que sabes",
  "newLine": false,
  "translation": {
   "text": "Mas claro que você sabe",
   "tips": [
    {
     "text": "claro que",
     "translatedText": "claro que / é claro que",
     "explanation": null
    },
    {
     "text": "sabes",
     "translatedText": "você sabe",
     "explanation": null
    }
   ]
  }
 },
 {
  "text": " ",
  "newLine": false,
  "translation": null
 },
 {
  "text": "lo que hago",
  "newLine": false,
  "translation": {
   "text": "o que eu faço",
   "tips": [
    {
     "text": "lo que",
     "translatedText": "o que / aquilo que",
     "explanation": null
    },
    {
     "text": "hago",
     "translatedText": "(eu) faço",
     "explanation": null
    }
   ]
  }
 },
 {
  "text": "! ",
  "newLine": false,
  "translation": null
 },
 {
  "text": "Soy médica",
  "newLine": false,
  "translation": {
   "text": "Sou médica",
   "tips": [
    {
     "text": "Soy",
     "translatedText": "(eu) sou",
     "explanation": "ser vs estar: para identidade/profissão (algo permanente) usa-se SER → \"soy médica\". Jamais \"estoy médica\". É o erro nº 1 do brasileiro; profissão é SEMPRE com ser."
    },
    {
     "text": "médica",
     "translatedText": "médica",
     "explanation": null
    }
   ]
  }
 },
 {
  "text": ". ",
  "newLine": false,
  "translation": null
 },
 {
  "text": "Trabajo en el hospital",
  "newLine": false,
  "translation": {
   "text": "Trabalho no hospital",
   "tips": [
    {
     "text": "Trabajo",
     "translatedText": "(eu) trabalho",
     "explanation": null
    },
    {
     "text": "en el hospital",
     "translatedText": "no hospital",
     "explanation": null
    }
   ]
  }
 },
 {
  "text": "»",
  "newLine": false,
  "translation": null
 },
 {
  "text": ", ",
  "newLine": false,
  "translation": null
 },
 {
  "text": "dijo su madre",
  "newLine": false,
  "translation": {
   "text": "disse sua mãe",
   "tips": [
    {
     "text": "dijo",
     "translatedText": "disse",
     "explanation": null
    }
   ]
  }
 },
 {
  "text": ". ",
  "newLine": false,
  "translation": null
 },
 {
  "text": "«",
  "newLine": false,
  "translation": null
 },
 {
  "text": "Hasta me has visitado",
  "newLine": false,
  "translation": {
   "text": "Você até me visitou",
   "tips": [
    {
     "text": "Hasta",
     "translatedText": "até (inclusive)",
     "explanation": null
    },
    {
     "text": "me has visitado",
     "translatedText": "você me visitou / tem me visitado",
     "explanation": null
    }
   ]
  }
 },
 {
  "text": " ",
  "newLine": false,
  "translation": null
 },
 {
  "text": "allí",
  "newLine": false,
  "translation": {
   "text": "lá / ali",
   "tips": [
    {
     "text": "allí",
     "translatedText": "lá / ali",
     "explanation": null
    }
   ]
  }
 },
 {
  "text": " ",
  "newLine": false,
  "translation": null
 },
 {
  "text": "un par de veces",
  "newLine": false,
  "translation": {
   "text": "umas duas vezes",
   "tips": [
    {
     "text": "un par de",
     "translatedText": "um par de / umas duas",
     "explanation": null
    },
    {
     "text": "veces",
     "translatedText": "vezes",
     "explanation": null
    }
   ]
  }
 },
 {
  "text": "»",
  "newLine": false,
  "translation": null
 },
 {
  "text": ".",
  "newLine": false,
  "translation": null
 },
 {
  "text": "«",
  "newLine": true,
  "translation": null
 },
 {
  "text": "Lo sé",
  "newLine": false,
  "translation": {
   "text": "Eu sei",
   "tips": [
    {
     "text": "Lo sé",
     "translatedText": "eu sei (isso)",
     "explanation": null
    }
   ]
  }
 },
 {
  "text": ", ",
  "newLine": false,
  "translation": null
 },
 {
  "text": "pero",
  "newLine": false,
  "translation": {
   "text": "mas",
   "tips": [
    {
     "text": "pero",
     "translatedText": "mas / porém",
     "explanation": null
    }
   ]
  }
 },
 {
  "text": " ",
  "newLine": false,
  "translation": null
 },
 {
  "text": "¿",
  "newLine": false,
  "translation": null
 },
 {
  "text": "qué haces",
  "newLine": false,
  "translation": {
   "text": "o que você faz",
   "tips": [
    {
     "text": "haces",
     "translatedText": "você faz",
     "explanation": null
    }
   ]
  }
 },
 {
  "text": " ",
  "newLine": false,
  "translation": null
 },
 {
  "text": "exactamente",
  "newLine": false,
  "translation": {
   "text": "exatamente",
   "tips": [
    {
     "text": "exactamente",
     "translatedText": "exatamente",
     "explanation": null
    }
   ]
  }
 },
 {
  "text": "? ",
  "newLine": false,
  "translation": null
 },
 {
  "text": "Mira",
  "newLine": false,
  "translation": {
   "text": "Olha",
   "tips": [
    {
     "text": "Mira",
     "translatedText": "olha / veja",
     "explanation": null
    }
   ]
  }
 },
 {
  "text": ", ",
  "newLine": false,
  "translation": null
 },
 {
  "text": "es como si no supiera",
  "newLine": false,
  "translation": {
   "text": "é como se eu não soubesse",
   "tips": [
    {
     "text": "como si",
     "translatedText": "como se",
     "explanation": "Eixo do subjuntivo (campeão!): \"como si\" SEMPRE pede o imperfeito do subjuntivo → \"como si no supiera\" = \"como se (eu) não soubesse\". Nunca use o presente depois de \"como si\"."
    },
    {
     "text": "no supiera",
     "translatedText": "não soubesse",
     "explanation": null
    }
   ]
  }
 },
 {
  "text": " ",
  "newLine": false,
  "translation": null
 },
 {
  "text": "los detalles",
  "newLine": false,
  "translation": {
   "text": "os detalhes",
   "tips": [
    {
     "text": "detalles",
     "translatedText": "detalhes",
     "explanation": null
    }
   ]
  }
 },
 {
  "text": "»",
  "newLine": false,
  "translation": null
 },
 {
  "text": ", ",
  "newLine": false,
  "translation": null
 },
 {
  "text": "respondió Ana",
  "newLine": false,
  "translation": {
   "text": "respondeu Ana",
   "tips": [
    {
     "text": "respondió",
     "translatedText": "respondeu",
     "explanation": null
    }
   ]
  }
 },
 {
  "text": ".",
  "newLine": false,
  "translation": null
 },
 {
  "text": "Su madre",
  "newLine": true,
  "translation": {
   "text": "Sua mãe",
   "tips": [
    {
     "text": "Su madre",
     "translatedText": "sua mãe / a mãe dela",
     "explanation": null
    }
   ]
  }
 },
 {
  "text": " ",
  "newLine": false,
  "translation": null
 },
 {
  "text": "estaba empezando a entender",
  "newLine": false,
  "translation": {
   "text": "estava começando a entender",
   "tips": [
    {
     "text": "estaba empezando",
     "translatedText": "estava começando",
     "explanation": null
    },
    {
     "text": "a entender",
     "translatedText": "a entender",
     "explanation": null
    }
   ]
  }
 },
 {
  "text": " ",
  "newLine": false,
  "translation": null
 },
 {
  "text": "lo que su hija",
  "newLine": false,
  "translation": {
   "text": "o que sua filha",
   "tips": [
    {
     "text": "su hija",
     "translatedText": "sua filha / a filha dela",
     "explanation": null
    }
   ]
  }
 },
 {
  "text": " ",
  "newLine": false,
  "translation": null
 },
 {
  "text": "quería decir",
  "newLine": false,
  "translation": {
   "text": "queria dizer",
   "tips": [
    {
     "text": "quería decir",
     "translatedText": "queria dizer / significava",
     "explanation": null
    }
   ]
  }
 },
 {
  "text": ".",
  "newLine": false,
  "translation": null
 },
 {
  "text": "«",
  "newLine": true,
  "translation": null
 },
 {
  "text": "Cuando la gente",
  "newLine": false,
  "translation": {
   "text": "Quando as pessoas",
   "tips": [
    {
     "text": "Cuando",
     "translatedText": "quando",
     "explanation": null
    },
    {
     "text": "la gente",
     "translatedText": "as pessoas / a gente",
     "explanation": null
    }
   ]
  }
 },
 {
  "text": " ",
  "newLine": false,
  "translation": null
 },
 {
  "text": "se enferma",
  "newLine": false,
  "translation": {
   "text": "adoece",
   "tips": [
    {
     "text": "se enferma",
     "translatedText": "adoece / fica doente",
     "explanation": null
    }
   ]
  }
 },
 {
  "text": ", ",
  "newLine": false,
  "translation": null
 },
 {
  "text": "va al hospital",
  "newLine": false,
  "translation": {
   "text": "vai ao hospital",
   "tips": [
    {
     "text": "va",
     "translatedText": "vai",
     "explanation": null
    },
    {
     "text": "al hospital",
     "translatedText": "ao hospital (a + el)",
     "explanation": null
    }
   ]
  }
 },
 {
  "text": "»",
  "newLine": false,
  "translation": null
 },
 {
  "text": ", ",
  "newLine": false,
  "translation": null
 },
 {
  "text": "dijo su madre",
  "newLine": false,
  "translation": {
   "text": "disse sua mãe",
   "tips": [
    {
     "text": "dijo",
     "translatedText": "disse",
     "explanation": null
    }
   ]
  }
 },
 {
  "text": ". ",
  "newLine": false,
  "translation": null
 },
 {
  "text": "«",
  "newLine": false,
  "translation": null
 },
 {
  "text": "Allí",
  "newLine": false,
  "translation": {
   "text": "Lá",
   "tips": [
    {
     "text": "Allí",
     "translatedText": "lá / ali",
     "explanation": null
    }
   ]
  }
 },
 {
  "text": " ",
  "newLine": false,
  "translation": null
 },
 {
  "text": "los cuidamos",
  "newLine": false,
  "translation": {
   "text": "cuidamos deles",
   "tips": [
    {
     "text": "los cuidamos",
     "translatedText": "nós os cuidamos / cuidamos deles",
     "explanation": null
    }
   ]
  }
 },
 {
  "text": ". ",
  "newLine": false,
  "translation": null
 },
 {
  "text": "Les damos",
  "newLine": false,
  "translation": {
   "text": "Damos a eles",
   "tips": [
    {
     "text": "Les damos",
     "translatedText": "damos a eles / lhes damos",
     "explanation": null
    }
   ]
  }
 },
 {
  "text": " ",
  "newLine": false,
  "translation": null
 },
 {
  "text": "la medicina correcta",
  "newLine": false,
  "translation": {
   "text": "o remédio certo",
   "tips": [
    {
     "text": "la medicina",
     "translatedText": "o remédio / a medicina",
     "explanation": null
    },
    {
     "text": "correcta",
     "translatedText": "correta / certa",
     "explanation": null
    }
   ]
  }
 },
 {
  "text": ", ",
  "newLine": false,
  "translation": null
 },
 {
  "text": "por ejemplo",
  "newLine": false,
  "translation": {
   "text": "por exemplo",
   "tips": [
    {
     "text": "por ejemplo",
     "translatedText": "por exemplo",
     "explanation": null
    }
   ]
  }
 },
 {
  "text": "»",
  "newLine": false,
  "translation": null
 },
 {
  "text": ".",
  "newLine": false,
  "translation": null
 },
 {
  "text": "«",
  "newLine": true,
  "translation": null
 },
 {
  "text": "Sí",
  "newLine": false,
  "translation": {
   "text": "Sim",
   "tips": [
    {
     "text": "Sí",
     "translatedText": "sim",
     "explanation": null
    }
   ]
  }
 },
 {
  "text": ", ",
  "newLine": false,
  "translation": null
 },
 {
  "text": "mamá",
  "newLine": false,
  "translation": {
   "text": "mamãe",
   "tips": [
    {
     "text": "mamá",
     "translatedText": "mamãe / mãe",
     "explanation": null
    }
   ]
  }
 },
 {
  "text": ", ",
  "newLine": false,
  "translation": null
 },
 {
  "text": "pero",
  "newLine": false,
  "translation": {
   "text": "mas",
   "tips": [
    {
     "text": "pero",
     "translatedText": "mas / porém",
     "explanation": null
    }
   ]
  }
 },
 {
  "text": " ",
  "newLine": false,
  "translation": null
 },
 {
  "text": "la maestra dijo",
  "newLine": false,
  "translation": {
   "text": "a professora disse",
   "tips": [
    {
     "text": "maestra",
     "translatedText": "professora",
     "explanation": null
    },
    {
     "text": "dijo",
     "translatedText": "disse",
     "explanation": null
    }
   ]
  }
 },
 {
  "text": " ",
  "newLine": false,
  "translation": null
 },
 {
  "text": "que hay",
  "newLine": false,
  "translation": {
   "text": "que há",
   "tips": [
    {
     "text": "hay",
     "translatedText": "há / existe(m)",
     "explanation": null
    }
   ]
  }
 },
 {
  "text": " ",
  "newLine": false,
  "translation": null
 },
 {
  "text": "muchos tipos diferentes",
  "newLine": false,
  "translation": {
   "text": "muitos tipos diferentes",
   "tips": [
    {
     "text": "muchos tipos",
     "translatedText": "muitos tipos",
     "explanation": null
    },
    {
     "text": "diferentes",
     "translatedText": "diferentes",
     "explanation": null
    }
   ]
  }
 },
 {
  "text": " ",
  "newLine": false,
  "translation": null
 },
 {
  "text": "de médicos",
  "newLine": false,
  "translation": {
   "text": "de médicos",
   "tips": [
    {
     "text": "médicos",
     "translatedText": "médicos",
     "explanation": null
    }
   ]
  }
 },
 {
  "text": ". ",
  "newLine": false,
  "translation": null
 },
 {
  "text": "Algunos cuidan",
  "newLine": false,
  "translation": {
   "text": "Alguns cuidam",
   "tips": [
    {
     "text": "Algunos",
     "translatedText": "alguns",
     "explanation": null
    },
    {
     "text": "cuidan",
     "translatedText": "cuidam",
     "explanation": null
    }
   ]
  }
 },
 {
  "text": " ",
  "newLine": false,
  "translation": null
 },
 {
  "text": "a los niños",
  "newLine": false,
  "translation": {
   "text": "das crianças",
   "tips": [
    {
     "text": "a los niños",
     "translatedText": "das crianças (lit. 'aos meninos')",
     "explanation": null
    }
   ]
  }
 },
 {
  "text": "; ",
  "newLine": false,
  "translation": null
 },
 {
  "text": "otros cuidan",
  "newLine": false,
  "translation": {
   "text": "outros cuidam",
   "tips": [
    {
     "text": "otros",
     "translatedText": "outros",
     "explanation": null
    }
   ]
  }
 },
 {
  "text": " ",
  "newLine": false,
  "translation": null
 },
 {
  "text": "a la gente mayor",
  "newLine": false,
  "translation": {
   "text": "dos idosos",
   "tips": [
    {
     "text": "la gente mayor",
     "translatedText": "os idosos / as pessoas mais velhas",
     "explanation": null
    }
   ]
  }
 },
 {
  "text": ". ",
  "newLine": false,
  "translation": null
 },
 {
  "text": "¿",
  "newLine": false,
  "translation": null
 },
 {
  "text": "Qué tipo eres tú",
  "newLine": false,
  "translation": {
   "text": "Que tipo você é",
   "tips": [
    {
     "text": "Qué tipo",
     "translatedText": "que tipo",
     "explanation": null
    },
    {
     "text": "eres tú",
     "translatedText": "você é",
     "explanation": null
    }
   ]
  }
 },
 {
  "text": "?",
  "newLine": false,
  "translation": null
 },
 {
  "text": "»",
  "newLine": false,
  "translation": null
 },
 {
  "text": ", ",
  "newLine": false,
  "translation": null
 },
 {
  "text": "preguntó Ana",
  "newLine": false,
  "translation": {
   "text": "perguntou Ana",
   "tips": [
    {
     "text": "preguntó",
     "translatedText": "perguntou",
     "explanation": null
    }
   ]
  }
 },
 {
  "text": ".",
  "newLine": false,
  "translation": null
 },
 {
  "text": "Su madre suspiró",
  "newLine": true,
  "translation": {
   "text": "Sua mãe suspirou",
   "tips": [
    {
     "text": "suspiró",
     "translatedText": "suspirou",
     "explanation": null
    }
   ]
  }
 },
 {
  "text": ". ",
  "newLine": false,
  "translation": null
 },
 {
  "text": "Amaba su trabajo",
  "newLine": false,
  "translation": {
   "text": "Amava seu trabalho",
   "tips": [
    {
     "text": "Amaba",
     "translatedText": "amava",
     "explanation": null
    },
    {
     "text": "su trabajo",
     "translatedText": "seu trabalho",
     "explanation": null
    }
   ]
  }
 },
 {
  "text": ", ",
  "newLine": false,
  "translation": null
 },
 {
  "text": "pero era",
  "newLine": false,
  "translation": {
   "text": "mas era",
   "tips": [
    {
     "text": "era",
     "translatedText": "era",
     "explanation": null
    }
   ]
  }
 },
 {
  "text": " ",
  "newLine": false,
  "translation": null
 },
 {
  "text": "un trabajo difícil",
  "newLine": false,
  "translation": {
   "text": "um trabalho difícil",
   "tips": [
    {
     "text": "difícil",
     "translatedText": "difícil",
     "explanation": null
    }
   ]
  }
 },
 {
  "text": ", ",
  "newLine": false,
  "translation": null
 },
 {
  "text": "y no pensaba",
  "newLine": false,
  "translation": {
   "text": "e não achava",
   "tips": [
    {
     "text": "no pensaba",
     "translatedText": "não pensava / não achava",
     "explanation": null
    }
   ]
  }
 },
 {
  "text": " ",
  "newLine": false,
  "translation": null
 },
 {
  "text": "que tendría que hablar",
  "newLine": false,
  "translation": {
   "text": "que teria que falar",
   "tips": [
    {
     "text": "tendría que",
     "translatedText": "teria que",
     "explanation": null
    },
    {
     "text": "hablar",
     "translatedText": "falar",
     "explanation": null
    }
   ]
  }
 },
 {
  "text": " ",
  "newLine": false,
  "translation": null
 },
 {
  "text": "de eso",
  "newLine": false,
  "translation": {
   "text": "sobre isso",
   "tips": [
    {
     "text": "de eso",
     "translatedText": "sobre isso / disso",
     "explanation": null
    }
   ]
  }
 },
 {
  "text": " ",
  "newLine": false,
  "translation": null
 },
 {
  "text": "con su hija",
  "newLine": false,
  "translation": {
   "text": "com sua filha",
   "tips": [
    {
     "text": "su hija",
     "translatedText": "sua filha",
     "explanation": null
    }
   ]
  }
 },
 {
  "text": " ",
  "newLine": false,
  "translation": null
 },
 {
  "text": "tan pronto",
  "newLine": false,
  "translation": {
   "text": "tão cedo",
   "tips": [
    {
     "text": "tan pronto",
     "translatedText": "tão cedo / tão logo",
     "explanation": null
    }
   ]
  }
 },
 {
  "text": ". ",
  "newLine": false,
  "translation": null
 },
 {
  "text": "Así que",
  "newLine": false,
  "translation": {
   "text": "Então",
   "tips": [
    {
     "text": "Así que",
     "translatedText": "então / por isso",
     "explanation": null
    }
   ]
  }
 },
 {
  "text": " ",
  "newLine": false,
  "translation": null
 },
 {
  "text": "se sentó en el sofá",
  "newLine": false,
  "translation": {
   "text": "sentou-se no sofá",
   "tips": [
    {
     "text": "se sentó",
     "translatedText": "sentou-se",
     "explanation": null
    },
    {
     "text": "el sofá",
     "translatedText": "o sofá",
     "explanation": null
    }
   ]
  }
 },
 {
  "text": ", ",
  "newLine": false,
  "translation": null
 },
 {
  "text": "y Ana hizo lo mismo",
  "newLine": false,
  "translation": {
   "text": "e Ana fez o mesmo",
   "tips": [
    {
     "text": "hizo",
     "translatedText": "fez",
     "explanation": null
    },
    {
     "text": "lo mismo",
     "translatedText": "o mesmo / a mesma coisa",
     "explanation": null
    }
   ]
  }
 },
 {
  "text": ". ",
  "newLine": false,
  "translation": null
 },
 {
  "text": "Su perro",
  "newLine": false,
  "translation": {
   "text": "Seu cachorro",
   "tips": [
    {
     "text": "perro",
     "translatedText": "cachorro / cão",
     "explanation": null
    }
   ]
  }
 },
 {
  "text": ", ",
  "newLine": false,
  "translation": null
 },
 {
  "text": "Ojos Azules",
  "newLine": false,
  "translation": {
   "text": "Ojos Azules",
   "tips": [
    {
     "text": "Ojos Azules",
     "translatedText": "Olhos Azuis (nome do cão)",
     "explanation": null
    }
   ]
  }
 },
 {
  "text": ", ",
  "newLine": false,
  "translation": null
 },
 {
  "text": "también entró",
  "newLine": false,
  "translation": {
   "text": "também entrou",
   "tips": [
    {
     "text": "también",
     "translatedText": "também",
     "explanation": null
    },
    {
     "text": "entró",
     "translatedText": "entrou",
     "explanation": null
    }
   ]
  }
 },
 {
  "text": " ",
  "newLine": false,
  "translation": null
 },
 {
  "text": "en la sala",
  "newLine": false,
  "translation": {
   "text": "na sala",
   "tips": [
    {
     "text": "la sala",
     "translatedText": "a sala",
     "explanation": null
    }
   ]
  }
 },
 {
  "text": " ",
  "newLine": false,
  "translation": null
 },
 {
  "text": "y se sentó",
  "newLine": false,
  "translation": {
   "text": "e se sentou",
   "tips": [
    {
     "text": "se sentó",
     "translatedText": "sentou-se",
     "explanation": null
    }
   ]
  }
 },
 {
  "text": " ",
  "newLine": false,
  "translation": null
 },
 {
  "text": "al lado de la niña",
  "newLine": false,
  "translation": {
   "text": "ao lado da menina",
   "tips": [
    {
     "text": "al lado de",
     "translatedText": "ao lado de",
     "explanation": null
    }
   ]
  }
 },
 {
  "text": ", ",
  "newLine": false,
  "translation": null
 },
 {
  "text": "como si él también",
  "newLine": false,
  "translation": {
   "text": "como se ele também",
   "tips": [
    {
     "text": "como si",
     "translatedText": "como se",
     "explanation": null
    },
    {
     "text": "él también",
     "translatedText": "ele também",
     "explanation": null
    }
   ]
  }
 },
 {
  "text": " ",
  "newLine": false,
  "translation": null
 },
 {
  "text": "estuviera interesado",
  "newLine": false,
  "translation": {
   "text": "estivesse interessado",
   "tips": [
    {
     "text": "estuviera interesado",
     "translatedText": "estivesse interessado",
     "explanation": null
    }
   ]
  }
 },
 {
  "text": " ",
  "newLine": false,
  "translation": null
 },
 {
  "text": "en la conversación",
  "newLine": false,
  "translation": {
   "text": "na conversa",
   "tips": [
    {
     "text": "la conversación",
     "translatedText": "a conversa",
     "explanation": null
    }
   ]
  }
 },
 {
  "text": ".",
  "newLine": false,
  "translation": null
 },
 {
  "text": "«",
  "newLine": true,
  "translation": null
 },
 {
  "text": "Cuido a las personas",
  "newLine": false,
  "translation": {
   "text": "Cuido das pessoas",
   "tips": [
    {
     "text": "Cuido",
     "translatedText": "(eu) cuido",
     "explanation": null
    },
    {
     "text": "a las personas",
     "translatedText": "das pessoas",
     "explanation": null
    }
   ]
  }
 },
 {
  "text": " ",
  "newLine": false,
  "translation": null
 },
 {
  "text": "que tienen cáncer",
  "newLine": false,
  "translation": {
   "text": "que têm câncer",
   "tips": [
    {
     "text": "tienen",
     "translatedText": "têm",
     "explanation": null
    },
    {
     "text": "cáncer",
     "translatedText": "câncer",
     "explanation": null
    }
   ]
  }
 },
 {
  "text": ". ",
  "newLine": false,
  "translation": null
 },
 {
  "text": "Es una enfermedad",
  "newLine": false,
  "translation": {
   "text": "É uma doença",
   "tips": [
    {
     "text": "Es",
     "translatedText": "é",
     "explanation": null
    },
    {
     "text": "una enfermedad",
     "translatedText": "uma doença",
     "explanation": null
    }
   ]
  }
 },
 {
  "text": " ",
  "newLine": false,
  "translation": null
 },
 {
  "text": "muy complicada",
  "newLine": false,
  "translation": {
   "text": "muito complicada",
   "tips": [
    {
     "text": "complicada",
     "translatedText": "complicada",
     "explanation": null
    }
   ]
  }
 },
 {
  "text": ", ",
  "newLine": false,
  "translation": null
 },
 {
  "text": "pero en la mayoría de los casos",
  "newLine": false,
  "translation": {
   "text": "mas na maioria dos casos",
   "tips": [
    {
     "text": "la mayoría de",
     "translatedText": "a maioria de",
     "explanation": null
    },
    {
     "text": "los casos",
     "translatedText": "os casos",
     "explanation": null
    }
   ]
  }
 },
 {
  "text": " ",
  "newLine": false,
  "translation": null
 },
 {
  "text": "los pacientes mejoran",
  "newLine": false,
  "translation": {
   "text": "os pacientes melhoram",
   "tips": [
    {
     "text": "los pacientes",
     "translatedText": "os pacientes",
     "explanation": null
    },
    {
     "text": "mejoran",
     "translatedText": "melhoram",
     "explanation": null
    }
   ]
  }
 },
 {
  "text": "»",
  "newLine": false,
  "translation": null
 },
 {
  "text": ", ",
  "newLine": false,
  "translation": null
 },
 {
  "text": "explicó su madre",
  "newLine": false,
  "translation": {
   "text": "explicou sua mãe",
   "tips": [
    {
     "text": "explicó",
     "translatedText": "explicou",
     "explanation": null
    }
   ]
  }
 },
 {
  "text": ".",
  "newLine": false,
  "translation": null
 },
 {
  "text": "«",
  "newLine": true,
  "translation": null
 },
 {
  "text": "¿",
  "newLine": false,
  "translation": null
 },
 {
  "text": "Qué es el cáncer",
  "newLine": false,
  "translation": {
   "text": "O que é o câncer",
   "tips": [
    {
     "text": "Qué es",
     "translatedText": "o que é",
     "explanation": null
    },
    {
     "text": "el cáncer",
     "translatedText": "o câncer",
     "explanation": null
    }
   ]
  }
 },
 {
  "text": "?",
  "newLine": false,
  "translation": null
 },
 {
  "text": "»",
  "newLine": false,
  "translation": null
 },
 {
  "text": ", ",
  "newLine": false,
  "translation": null
 },
 {
  "text": "preguntó Ana",
  "newLine": false,
  "translation": {
   "text": "perguntou Ana",
   "tips": [
    {
     "text": "preguntó",
     "translatedText": "perguntou",
     "explanation": null
    }
   ]
  }
 },
 {
  "text": ".",
  "newLine": false,
  "translation": null
 },
 {
  "text": "«",
  "newLine": true,
  "translation": null
 },
 {
  "text": "Mira",
  "newLine": false,
  "translation": {
   "text": "Olha",
   "tips": [
    {
     "text": "Mira",
     "translatedText": "olha / veja",
     "explanation": null
    }
   ]
  }
 },
 {
  "text": ", ",
  "newLine": false,
  "translation": null
 },
 {
  "text": "nuestros cuerpos",
  "newLine": false,
  "translation": {
   "text": "nossos corpos",
   "tips": [
    {
     "text": "nuestros cuerpos",
     "translatedText": "nossos corpos",
     "explanation": null
    }
   ]
  }
 },
 {
  "text": " ",
  "newLine": false,
  "translation": null
 },
 {
  "text": "están hechos",
  "newLine": false,
  "translation": {
   "text": "são feitos",
   "tips": [
    {
     "text": "están hechos",
     "translatedText": "são feitos / estão feitos",
     "explanation": null
    }
   ]
  }
 },
 {
  "text": " ",
  "newLine": false,
  "translation": null
 },
 {
  "text": "de partes muy pequeñas",
  "newLine": false,
  "translation": {
   "text": "de partes muito pequenas",
   "tips": [
    {
     "text": "partes",
     "translatedText": "partes",
     "explanation": null
    },
    {
     "text": "muy pequeñas",
     "translatedText": "muito pequenas",
     "explanation": null
    }
   ]
  }
 },
 {
  "text": " ",
  "newLine": false,
  "translation": null
 },
 {
  "text": "que se llaman células",
  "newLine": false,
  "translation": {
   "text": "que se chamam células",
   "tips": [
    {
     "text": "se llaman",
     "translatedText": "se chamam / chamam-se",
     "explanation": null
    },
    {
     "text": "células",
     "translatedText": "células",
     "explanation": null
    }
   ]
  }
 },
 {
  "text": ". ",
  "newLine": false,
  "translation": null
 },
 {
  "text": "A veces",
  "newLine": false,
  "translation": {
   "text": "Às vezes",
   "tips": [
    {
     "text": "A veces",
     "translatedText": "às vezes",
     "explanation": null
    }
   ]
  }
 },
 {
  "text": ", ",
  "newLine": false,
  "translation": null
 },
 {
  "text": "las células crecen",
  "newLine": false,
  "translation": {
   "text": "as células crescem",
   "tips": [
    {
     "text": "crecen",
     "translatedText": "crescem",
     "explanation": null
    }
   ]
  }
 },
 {
  "text": " ",
  "newLine": false,
  "translation": null
 },
 {
  "text": "demasiado",
  "newLine": false,
  "translation": {
   "text": "demais",
   "tips": [
    {
     "text": "demasiado",
     "translatedText": "demais / demasiado",
     "explanation": null
    }
   ]
  }
 },
 {
  "text": ", ",
  "newLine": false,
  "translation": null
 },
 {
  "text": "y eso no es bueno",
  "newLine": false,
  "translation": {
   "text": "e isso não é bom",
   "tips": [
    {
     "text": "eso",
     "translatedText": "isso",
     "explanation": null
    },
    {
     "text": "no es bueno",
     "translatedText": "não é bom",
     "explanation": null
    }
   ]
  }
 },
 {
  "text": ". ",
  "newLine": false,
  "translation": null
 },
 {
  "text": "Eso es lo que",
  "newLine": false,
  "translation": {
   "text": "Isso é o que",
   "tips": [
    {
     "text": "lo que",
     "translatedText": "o que / aquilo que",
     "explanation": null
    }
   ]
  }
 },
 {
  "text": " ",
  "newLine": false,
  "translation": null
 },
 {
  "text": "llamamos cáncer",
  "newLine": false,
  "translation": {
   "text": "chamamos de câncer",
   "tips": [
    {
     "text": "llamamos",
     "translatedText": "chamamos",
     "explanation": null
    }
   ]
  }
 },
 {
  "text": "»",
  "newLine": false,
  "translation": null
 },
 {
  "text": ", ",
  "newLine": false,
  "translation": null
 },
 {
  "text": "dijo la madre",
  "newLine": false,
  "translation": {
   "text": "disse a mãe",
   "tips": [
    {
     "text": "dijo",
     "translatedText": "disse",
     "explanation": null
    }
   ]
  }
 },
 {
  "text": ", ",
  "newLine": false,
  "translation": null
 },
 {
  "text": "y después decidió",
  "newLine": false,
  "translation": {
   "text": "e depois decidiu",
   "tips": [
    {
     "text": "después",
     "translatedText": "depois",
     "explanation": null
    },
    {
     "text": "decidió",
     "translatedText": "decidiu",
     "explanation": null
    }
   ]
  }
 },
 {
  "text": " ",
  "newLine": false,
  "translation": null
 },
 {
  "text": "cambiar un poco de tema",
  "newLine": false,
  "translation": {
   "text": "mudar um pouco de assunto",
   "tips": [
    {
     "text": "cambiar",
     "translatedText": "mudar",
     "explanation": null
    },
    {
     "text": "de tema",
     "translatedText": "de assunto / de tema",
     "explanation": null
    }
   ]
  }
 },
 {
  "text": ". ",
  "newLine": false,
  "translation": null
 },
 {
  "text": "«",
  "newLine": false,
  "translation": null
 },
 {
  "text": "Mi padre",
  "newLine": false,
  "translation": {
   "text": "Meu pai",
   "tips": [
    {
     "text": "Mi padre",
     "translatedText": "meu pai",
     "explanation": null
    }
   ]
  }
 },
 {
  "text": ", ",
  "newLine": false,
  "translation": null
 },
 {
  "text": "tu abuelo",
  "newLine": false,
  "translation": {
   "text": "seu avô",
   "tips": [
    {
     "text": "tu abuelo",
     "translatedText": "seu avô / teu avô",
     "explanation": null
    }
   ]
  }
 },
 {
  "text": ", ",
  "newLine": false,
  "translation": null
 },
 {
  "text": "también era médico",
  "newLine": false,
  "translation": {
   "text": "também era médico",
   "tips": [
    {
     "text": "también",
     "translatedText": "também",
     "explanation": null
    },
    {
     "text": "era médico",
     "translatedText": "era médico",
     "explanation": null
    }
   ]
  }
 },
 {
  "text": ". ",
  "newLine": false,
  "translation": null
 },
 {
  "text": "Era el tipo de médico",
  "newLine": false,
  "translation": {
   "text": "Era o tipo de médico",
   "tips": [
    {
     "text": "el tipo de",
     "translatedText": "o tipo de",
     "explanation": null
    }
   ]
  }
 },
 {
  "text": " ",
  "newLine": false,
  "translation": null
 },
 {
  "text": "que cuidaba a los niños",
  "newLine": false,
  "translation": {
   "text": "que cuidava das crianças",
   "tips": [
    {
     "text": "cuidaba",
     "translatedText": "cuidava",
     "explanation": null
    },
    {
     "text": "a los niños",
     "translatedText": "das crianças",
     "explanation": null
    }
   ]
  }
 },
 {
  "text": "; ",
  "newLine": false,
  "translation": null
 },
 {
  "text": "mi madre",
  "newLine": false,
  "translation": {
   "text": "minha mãe",
   "tips": [
    {
     "text": "mi madre",
     "translatedText": "minha mãe",
     "explanation": null
    }
   ]
  }
 },
 {
  "text": ", ",
  "newLine": false,
  "translation": null
 },
 {
  "text": "tu abuela",
  "newLine": false,
  "translation": {
   "text": "sua avó",
   "tips": [
    {
     "text": "tu abuela",
     "translatedText": "sua avó / tua avó",
     "explanation": null
    }
   ]
  }
 },
 {
  "text": ", ",
  "newLine": false,
  "translation": null
 },
 {
  "text": "era profesora de ciencias",
  "newLine": false,
  "translation": {
   "text": "era professora de ciências",
   "tips": [
    {
     "text": "profesora",
     "translatedText": "professora",
     "explanation": null
    },
    {
     "text": "ciencias",
     "translatedText": "ciências",
     "explanation": null
    }
   ]
  }
 },
 {
  "text": ". ",
  "newLine": false,
  "translation": null
 },
 {
  "text": "Ahora están jubilados",
  "newLine": false,
  "translation": {
   "text": "Agora estão aposentados",
   "tips": [
    {
     "text": "Ahora",
     "translatedText": "agora",
     "explanation": null
    },
    {
     "text": "están jubilados",
     "translatedText": "estão aposentados",
     "explanation": "Falso amigo campeão: \"jubilado/a\" = \"aposentado(a)\", e \"jubilarse\" = \"aposentar-se\". Nada a ver com \"jubilar\" (de alegria); o nosso \"jubilado\" se diz \"contento/alegre\". Note também ESTAR (estado): \"están jubilados\"."
    }
   ]
  }
 },
 {
  "text": ", ",
  "newLine": false,
  "translation": null
 },
 {
  "text": "lo que quiere decir",
  "newLine": false,
  "translation": {
   "text": "o que significa",
   "tips": [
    {
     "text": "quiere decir",
     "translatedText": "significa / quer dizer",
     "explanation": null
    }
   ]
  }
 },
 {
  "text": " ",
  "newLine": false,
  "translation": null
 },
 {
  "text": "que ya no tienen que trabajar",
  "newLine": false,
  "translation": {
   "text": "que já não têm que trabalhar",
   "tips": [
    {
     "text": "ya no",
     "translatedText": "já não / não mais",
     "explanation": null
    },
    {
     "text": "tienen que trabajar",
     "translatedText": "têm que trabalhar",
     "explanation": null
    }
   ]
  }
 },
 {
  "text": "»",
  "newLine": false,
  "translation": null
 },
 {
  "text": ", ",
  "newLine": false,
  "translation": null
 },
 {
  "text": "continuó",
  "newLine": false,
  "translation": {
   "text": "continuou",
   "tips": [
    {
     "text": "continuó",
     "translatedText": "continuou",
     "explanation": null
    }
   ]
  }
 },
 {
  "text": ".",
  "newLine": false,
  "translation": null
 }
]
